{
  "kind": "singleType",
  "collectionName": "proyects_pages",
  "info": {
    "singularName": "proyects-page",
    "pluralName": "proyects-pages",
    "displayName": "proyectsPage",
    "description": ""
  },
  "options": {
    "draftAndPublish": true
  },
  "pluginOptions": {
    "i18n": {
      "localized": true
    }
  },
  "attributes": {
    "title": {
      "pluginOptions": {
        "i18n": {
          "localized": true
        }
      },
      "type": "string",
      "required": true
    },
    "image": {
      "type": "media",
      "multiple": false,
      "required": true,
      "allowedTypes": [
        "images"
      ],
      "pluginOptions": {
        "i18n": {
          "localized": true
        }
      }
    }
  }
}
